calculator/__init__.py
shreyascal-0.1.dist-info/LICENCE
shreyascal-0.1.dist-info/METADATA
shreyascal-0.1.dist-info/WHEEL
shreyascal-0.1.dist-info/top_level.txt
shreyascal-0.1.dist-info/RECORD
