Metadata-Version: 2.1
Name: shreyascal
Version: 0.1
Summary: this is very basic calculator for maths opertaions
Home-page: UNKNOWN
Author: shreyas zadge
Author-email: zadgeshreyas@gmail.com
License: UNKNOWN
Platform: UNKNOWN
Classifier: Programming Language :: Python :: 3
Classifier: License :: OSI Approved :: MIT License
Classifier: Operating System :: OS Independent
